Zennin-1.1.0.data/data/share/doc/zennin/quotebook.txt
Zennin-1.1.0.data/data/share/man/man1/zennin.1
zennin/__init__.py
zennin/quotebook.py
zennin/quotebook.txt
Zennin-1.1.0.dist-info/LICENSE
Zennin-1.1.0.dist-info/METADATA
Zennin-1.1.0.dist-info/WHEEL
Zennin-1.1.0.dist-info/entry_points.txt
Zennin-1.1.0.dist-info/top_level.txt
Zennin-1.1.0.dist-info/RECORD
