Metadata-Version: 2.1
Name: Zennin
Version: 1.1.0
Summary: Print custom quotes on your terminal.
Author-email: Marcelo Galván <marcelo_galvan@protonmail.com>
Project-URL: Homepage, https://github.com/Erymer/zennin
Classifier: Programming Language :: Python :: 3
Classifier: License :: OSI Approved :: GNU General Public License v3 (GPLv3)
Classifier: Operating System :: POSIX :: Linux
Classifier: Development Status :: 5 - Production/Stable
Classifier: Topic :: Utilities
Classifier: Intended Audience :: End Users/Desktop
Requires-Python: >=3.10
License-File: LICENSE
